smartside
